{
    "kind": "collectionType",
    "collectionName": "articles",
    "info": {
        "singularName": "article",
        "pluralName": "articles",
        "displayName": "Article",
        "description": "Blog articles"
    },
    "options": {
        "draftAndPublish": true
    },
    "pluginOptions": {},
    "attributes": {
        "title": {
            "type": "string",
            "required": true
        },
        "description": {
            "type": "text",
            "required": true
        },
        "content": {
            "type": "customField",
            "customField": "plugin::tinymce.tinymce"
        },
        "slug": {
            "type": "uid",
            "targetField": "title",
            "required": true
        },
        "image": {
            "type": "media",
            "multiple": false,
            "required": false,
            "allowedTypes": [
                "images",
                "files",
                "videos",
                "audios"
            ]
        },
        "category": {
            "type": "relation",
            "relation": "manyToOne",
            "target": "api::category.category",
            "inversedBy": "articles"
        },
        "author": {
            "type": "relation",
            "relation": "manyToOne",
            "target": "api::author.author",
            "inversedBy": "articles"
        },
        "seoTitle": {
            "type": "string"
        },
        "seoDescription": {
            "type": "text"
        },
        "keywords": {
            "type": "text"
        },
        "canonicalUrl": {
            "type": "string"
        }
    }
}
